symply/__init__.py
symply/symply.py
symply/watcher.py
symply-0.1.2.dist-info/LICENSE
symply-0.1.2.dist-info/METADATA
symply-0.1.2.dist-info/WHEEL
symply-0.1.2.dist-info/entry_points.txt
symply-0.1.2.dist-info/RECORD
