Metadata-Version: 2.1
Name: symply
Version: 0.1.2
Summary: Effortless Symlink Management as a Python Package!
License: MIT
Author: Spoked
Author-email: dreu.lavelle@gmail.com
Requires-Python: >=3.11,<4.0
Classifier: License :: OSI Approved :: MIT License
Classifier: Programming Language :: Python :: 3
Classifier: Programming Language :: Python :: 3.11
Classifier: Programming Language :: Python :: 3.12
Requires-Dist: watchdog (>=4.0.0,<5.0.0)
